{
  "EffectShadowIconType": "dropShadow",
  "EffectShadowIconRadius": 4,
  "EffectShadowIconColor": "rgba(0, 0, 0, 0.25)",
  "EffectShadowIconOffsetX": 0,
  "EffectShadowIconOffsetY": 4,
  "EffectShadowIconSpread": 0,
  "EffectShadowHighType": "dropShadow",
  "EffectShadowHighRadius": 4,
  "EffectShadowHighColor": "rgba(0, 0, 0, 0.25)",
  "EffectShadowHighOffsetX": 0,
  "EffectShadowHighOffsetY": 4,
  "EffectShadowHighSpread": 0,
  "EffectShadowHighTopType": "dropShadow",
  "EffectShadowHighTopRadius": 10,
  "EffectShadowHighTopColor": "rgba(30, 5, 39, 0.08)",
  "EffectShadowHighTopOffsetX": 0,
  "EffectShadowHighTopOffsetY": -2,
  "EffectShadowHighTopSpread": 0,
  "EffectShadowLowType": "dropShadow",
  "EffectShadowLowRadius": 4,
  "EffectShadowLowColor": "rgba(30, 5, 39, 0.16)",
  "EffectShadowLowOffsetX": 0,
  "EffectShadowLowOffsetY": 1,
  "EffectShadowLowSpread": 0
}